prosecode/__init__.py
prosecode/chunk.py
prosecode/chunk_extension.py
prosecode/cli.py
prosecode/displaymath_extension.py
prosecode/htmltolatexparser.py
prosecode/tangle.py
prosecode/weave.py
prosecode-0.2.0.dist-info/LICENSE
prosecode-0.2.0.dist-info/METADATA
prosecode-0.2.0.dist-info/WHEEL
prosecode-0.2.0.dist-info/entry_points.txt
prosecode-0.2.0.dist-info/top_level.txt
prosecode-0.2.0.dist-info/RECORD
