Metadata-Version: 2.1
Name: prosecode
Version: 0.2.0
Summary: Literate programming in Python from markdown to LaTeX.
Home-page: https://donsheehy.github.io/prosecode/
Author: Donald R. Sheehy
Author-email: don.r.sheehy@gmail.com
License: UNKNOWN
Platform: UNKNOWN
Classifier: Programming Language :: Python :: 3
Classifier: License :: OSI Approved :: MIT License
Classifier: Operating System :: OS Independent
Requires-Python: >=3.6
Requires-Dist: Markdown
Requires-Dist: Click
Requires-Dist: Pygments
